dedi_link/__init__.py
dedi_link/data/bin/libpow.dll
dedi_link/data/bin/libpow.so
dedi_link/etc/__init__.py
dedi_link/etc/enums.py
dedi_link/etc/libpow/__init__.py
dedi_link/etc/libpow/libpow.py
dedi_link/model/__init__.py
dedi_link/model/base.py
dedi_link/model/crypto_key.py
dedi_link/model/network.py
dedi_link/model/node.py
dedi_link/model/user.py
dedi_link/model/network_message/__init__.py
dedi_link/model/network_message/management_key.py
dedi_link/model/network_message/message_metadata.py
dedi_link/model/network_message/network_message.py
dedi_link/model/network_message/auth_message/__init__.py
dedi_link/model/network_message/auth_message/connect.py
dedi_link/model/network_message/auth_message/invite.py
dedi_link/model/network_message/auth_message/invite_response.py
dedi_link/model/network_message/auth_message/notification.py
dedi_link/model/network_message/auth_message/request.py
dedi_link/model/network_message/auth_message/request_response.py
dedi_link/model/network_message/route_message/__init__.py
dedi_link/model/network_message/route_message/envelope.py
dedi_link/model/network_message/route_message/notification.py
dedi_link/model/network_message/route_message/request.py
dedi_link/model/network_message/route_message/response.py
dedi_link/model/network_message/sync_message/__init__.py
dedi_link/model/network_message/sync_message/node.py
dedi_link/model/network_message/sync_message/request.py
dedi_link-1.0.0a1.dist-info/licenses/LICENSE
dedi_link-1.0.0a1.dist-info/METADATA
dedi_link-1.0.0a1.dist-info/WHEEL
dedi_link-1.0.0a1.dist-info/top_level.txt
dedi_link-1.0.0a1.dist-info/RECORD
