Metadata-Version: 2.4
Name: dedi-link
Version: 1.0.0a1
Summary: Decentralised Discovery Link
Author-email: Firefox2100 <wangyunze16@gmail.com>
License-Expression: MIT
Project-URL: Homepage, https://github.com/Firefox2100/dedi-link
Project-URL: Repository, https://github.com/Firefox2100/dedi-link.git
Project-URL: Issues, https://github.com/Firefox2100/dedi-link/issues
Classifier: Development Status :: 3 - Alpha
Classifier: Intended Audience :: Developers
Classifier: Programming Language :: Python :: 3
Classifier: Programming Language :: Python :: 3.11
Classifier: Intended Audience :: Science/Research
Classifier: Operating System :: OS Independent
Requires-Python: >=3.11
License-File: LICENSE
Requires-Dist: cffi~=2.0.0
Requires-Dist: cryptography~=46.0.3
Requires-Dist: pydantic~=2.11.9
Provides-Extra: test
Requires-Dist: deepdiff~=8.6.1; extra == "test"
Requires-Dist: pytest~=8.4.2; extra == "test"
Requires-Dist: pytest-asyncio~=1.2.0; extra == "test"
Requires-Dist: pytest-cov~=7.0.0; extra == "test"
Requires-Dist: pylint~=4.0.1; extra == "test"
Dynamic: license-file
